mkpatcher/__init__.py
mkpatcher/__meta__.py
mkpatcher/extension.py
mkpatcher-1.0.2.dist-info/LICENSE-APACHE
mkpatcher-1.0.2.dist-info/LICENSE-MIT
mkpatcher-1.0.2.dist-info/METADATA
mkpatcher-1.0.2.dist-info/WHEEL
mkpatcher-1.0.2.dist-info/top_level.txt
mkpatcher-1.0.2.dist-info/RECORD
