Metadata-Version: 2.1
Name: mkpatcher
Version: 1.0.2
Summary: Python-Markdown extension allowing arbitrary scripts to modify MkDocs input files
Home-page: https://github.com/ofek/mkpatcher
Author: Ofek Lev
Author-email: ofekmeister@gmail.com
License: Apache-2.0 OR MIT
Project-URL: Documentation, https://github.com/ofek/mkpatcher#readme
Project-URL: Source Code, https://github.com/ofek/mkpatcher
Project-URL: Bug Tracker, https://github.com/ofek/mkpatcher/issues
Keywords: markdown,extensions,mkdocs,plugins
Platform: UNKNOWN
Classifier: Development Status :: 5 - Production/Stable
Classifier: Environment :: Console
Classifier: License :: OSI Approved :: Apache Software License
Classifier: License :: OSI Approved :: MIT License
Classifier: Natural Language :: English
Classifier: Operating System :: OS Independent
Classifier: Programming Language :: Python
Classifier: Programming Language :: Python :: 3 :: Only
Classifier: Programming Language :: Python :: 3.6
Classifier: Programming Language :: Python :: 3.7
Classifier: Programming Language :: Python :: 3.8
Classifier: Programming Language :: Python :: Implementation :: CPython
Classifier: Programming Language :: Python :: Implementation :: PyPy
Classifier: Topic :: Internet :: WWW/HTTP :: Dynamic Content
Classifier: Topic :: Software Development :: Libraries :: Python Modules
Classifier: Topic :: Text Processing :: Filters
Classifier: Topic :: Text Processing :: Markup :: HTML
Requires-Python: >=3.6
Requires-Dist: Markdown (>=3.2.1)
